Workbook

Sheet Dashboard1
A1: SALES PERFORMANCE DASHBOARD
A3: Executive view • Completed orders are used for performance KPIs and sales analysis
A5: Total Orders | D5: Total Sales | G5: Completed Sales | J5: Units Sold | M5: Completion Rate
A6: =Analysis!B4 | D6: =Analysis!B5 | G6: =Analysis!B6 | J6: =Analysis!B7 | M6: =Analysis!B9
A39: HOW TO USE THIS DASHBOARD
A40: 1. Update or paste new rows into the Sales_Data table.
A41: 2. Use the Analysis sheet to inspect category, city, payment, product, status and monthly performance.
A42: 3. The Dashboard focuses on completed orders for operational sales performance.
A43: 4. Recalculate formulas in Excel after adding data. For a fully interactive PivotTable/Slicer version, create PivotTables from the SalesData table and add Slicers.

Sheet Dashboard

Sheet Sales_Data
A1: Order_ID | B1: Order_Date | C1: Customer_Name | D1: Gender | E1: Age | F1: City | G1: Product | H1: Category | I1: Quantity | J1: Unit_Price | K1: Discount | L1: Total_Amount | M1: Payment_Method | N1: Status | O1: Month | P1: Year | Q1: Net_Sales | R1: Completed_Sales | S1: Cancelled_Sales
A2: 1001 | B2: 46196 | C2: Sophia Patel | D2: Male | E2: 55 | F2: Leipzig | G2: Headphones | H2: Accessories | I2: 2 | J2: 63.48 | K2: 0 | L2: 126.96 | M2: Card | N2: Completed | O2: =TEXT(B2,"mmm") | P2: =YEAR(B2) | Q2: =L2*(1-K2) | R2: =IF(N2="Completed",L2,0) | S2: =IF(N2="Cancelled",L2,0)
A3: 1002 | B3: 46073 | C3: Liam Brown | D3: Female | E3: 32 | F3: Stuttgart | G3: Mouse | H3: Accessories | I3: 5 | J3: 54.13 | K3: 0.2 | L3: 216.52 | M3: Bank Transfer | N3: Completed | O3: =TEXT(B3,"mmm") | P3: =YEAR(B3) | Q3: =L3*(1-K3) | R3: =IF(N3="Completed",L3,0) | S3: =IF(N3="Cancelled",L3,0)
A4: 1003 | B4: 46109 | C4: Aarav Smith | D4: Male | E4: 23 | F4: Leipzig | G4: Desk | H4: Furniture | I4: 3 | J4: 282.81 | K4: 0.05 | L4: 806.01 | M4: Card | N4: Completed | O4: =TEXT(B4,"mmm") | P4: =YEAR(B4) | Q4: =L4*(1-K4) | R4: =IF(N4="Completed",L4,0) | S4: =IF(N4="Cancelled",L4,0)
A5: 1004 | B5: 46054 | C5: Isla Martin | D5: Female | E5: 23 | F5: Cologne | G5: Headphones | H5: Accessories | I5: 1 | J5: 139.46 | K5: 0.2 | L5: 111.57 | M5: Bank Transfer | N5: Cancelled | O5: =TEXT(B5,"mmm") | P5: =YEAR(B5) | Q5: =L5*(1-K5) | R5: =IF(N5="Completed",L5,0) | S5: =IF(N5="Cancelled",L5,0)
A6: 1005 | B6: 46097 | C6: Isla Martin | D6: Male | E6: 32 | F6: Hamburg | G6: Mouse | H6: Accessories | I6: 1 | J6: 17.98 | K6: 0.05 | L6: 17.08 | M6: PayPal | N6: Completed | O6: =TEXT(B6,"mmm") | P6: =YEAR(B6) | Q6: =L6*(1-K6) | R6: =IF(N6="Completed",L6,0) | S6: =IF(N6="Cancelled",L6,0)
A7: 1006 | B7: 46202 | C7: Leo Wilson | D7: Male | E7: 28 | F7: Frankfurt | G7: Keyboard | H7: Accessories | I7: 3 | J7: 58.75 | K7: 0.1 | L7: 158.62 | M7: Card | N7: Pending | O7: =TEXT(B7,"mmm") | P7: =YEAR(B7) | Q7: =L7*(1-K7) | R7: =IF(N7="Completed",L7,0) | S7: =IF(N7="Cancelled",L7,0)
A8: 1007 | B8: 46081 | C8: Daniel Miller | D8: Male | E8: 38 | F8: Leipzig | G8: USB Hub | H8: Accessories | I8: 2 | J8: 54.23 | K8: 0 | L8: 108.46 | M8: PayPal | N8: Completed | O8: =TEXT(B8,"mmm") | P8: =YEAR(B8) | Q8: =L8*(1-K8) | R8: =IF(N8="Completed",L8,0) | S8: =IF(N8="Cancelled",L8,0)
A9: 1008 | B9: 46187 | C9: Lucas Martin | D9: Female | E9: 27 | F9: Cologne | G9: Office Chair | H9: Furniture | I9: 2 | J9: 303.52 | K9: 0.15 | L9: 515.98 | M9: Card | N9: Completed | O9: =TEXT(B9,"mmm") | P9: =YEAR(B9) | Q9: =L9*(1-K9) | R9: =IF(N9="Completed",L9,0) | S9: =IF(N9="Cancelled",L9,0)
A10: 1009 | B10: 46125 | C10: Grace Thomas | D10: Female | E10: 32 | F10: Munich | G10: Headphones | H10: Accessories | I10: 5 | J10: 94.27 | K10: 0.2 | L10: 377.08 | M10: Bank Transfer | N10: Pending | O10: =TEXT(B10,"mmm") | P10: =YEAR(B10) | Q10: =L10*(1-K10) | R10: =IF(N10="Completed",L10,0) | S10: =IF(N10="Cancelled",L10,0)
A11: 1010 | B11: 46175 | C11: Liam Patel | D11: Male | E11: 42 | F11: Leipzig | G11: Monitor | H11: Electronics | I11: 2 | J11: 338.23 | K11: 0.15 | L11: 574.99 | M11: Bank Transfer | N11: Pending | O11: =TEXT(B11,"mmm") | P11: =YEAR(B11) | Q11: =L11*(1-K11) | R11: =IF(N11="Completed",L11,0) | S11: =IF(N11="Cancelled",L11,0)
A12: 1011 | B12: 46197 | C12: Rohan Miller | D12: Female | E12: 39 | F12: Hamburg | G12: USB Hub | H12: Accessories | I12: 1 | J12: 54.01 | K12: 0 | L12: 54.01 | M12: PayPal | N12: Pending | O12: =TEXT(B12,"mmm") | P12: =YEAR(B12) | Q12: =L12*(1-K12) | R12: =IF(N12="Completed",L12,0) | S12: =IF(N12="Cancelled",L12,0)
A13: 1012 | B13: 46152 | C13: Olivia Anderson | D13: Male | E13: 37 | F13: Frankfurt | G13: Laptop | H13: Electronics | I13: 3 | J13: 1378.92 | K13: 0.05 | L13: 3929.92 | M13: Card | N13: Completed | O13: =TEXT(B13,"mmm") | P13: =YEAR(B13) | Q13: =L13*(1-K13) | R13: =IF(N13="Completed",L13,0) | S13: =IF(N13="Cancelled",L13,0)
... A101: 1100 | B101: 46048 | C101: Isla Brown | D101: Female | E101: 52 | F101: Düsseldorf | G101: Webcam | H101: Electronics | I101: 4 | J101: 154.07 | K101: 0.1 | L101: 554.65 | M101: Card | N101: Pending | O101: =TEXT(B101,"mmm") | P101: =YEAR(B101) | Q101: =L101*(1-K101) | R101: =IF(N101="Completed",L101,0) | S101: =IF(N101="Cancelled",L101,0)

Sheet Analysis
A1: SALES ANALYSIS
A3: KEY KPIs | D3: SALES BY CATEGORY | G3: MONTHLY SALES TREND
A4: Total Orders | B4: =COUNTA('Sales_Data'!$A$2:$A$101) | D4: Category | E4: Orders | F4: Sales | G4: Month | H4: Orders | I4: Sales
A5: Total Sales | B5: =SUM('Sales_Data'!$L$2:$L$101) | D5: Accessories | E5: =COUNTIFS('Sales_Data'!$H$2:$H$101,D5,'Sales_Data'!$N$2:$N$101,"Completed") | F5: =SUMIFS('Sales_Data'!$L$2:$L$101,'Sales_Data'!$H$2:$H$101,D5,'Sales_Data'!$N$2:$N$101,"Completed") | G5: 46023 | H5: =COUNTIFS('Sales_Data'!$B$2:$B$101,">="&G5,'Sales_Data'!$B$2:$B$101,"<"&EDATE(G5,1),'Sales_Data'!$N$2:$N$101,"Completed") | I5: =SUMIFS('Sales_Data'!$L$2:$L$101,'Sales_Data'!$B$2:$B$101,">="&G5,'Sales_Data'!$B$2:$B$101,"<"&EDATE(G5,1),'Sales_Data'!$N$2:$N$101,"Completed")
A6: Completed Sales | B6: =SUMIF('Sales_Data'!$N$2:$N$101,"Completed",'Sales_Data'!$L$2:$L$101) | D6: Electronics | E6: =COUNTIFS('Sales_Data'!$H$2:$H$101,D6,'Sales_Data'!$N$2:$N$101,"Completed") | F6: =SUMIFS('Sales_Data'!$L$2:$L$101,'Sales_Data'!$H$2:$H$101,D6,'Sales_Data'!$N$2:$N$101,"Completed") | G6: 46054 | H6: =COUNTIFS('Sales_Data'!$B$2:$B$101,">="&G6,'Sales_Data'!$B$2:$B$101,"<"&EDATE(G6,1),'Sales_Data'!$N$2:$N$101,"Completed") | I6: =SUMIFS('Sales_Data'!$L$2:$L$101,'Sales_Data'!$B$2:$B$101,">="&G6,'Sales_Data'!$B$2:$B$101,"<"&EDATE(G6,1),'Sales_Data'!$N$2:$N$101,"Completed")
A7: Units Sold | B7: =SUMIF('Sales_Data'!$N$2:$N$101,"Completed",'Sales_Data'!$I$2:$I$101) | D7: Furniture | E7: =COUNTIFS('Sales_Data'!$H$2:$H$101,D7,'Sales_Data'!$N$2:$N$101,"Completed") | F7: =SUMIFS('Sales_Data'!$L$2:$L$101,'Sales_Data'!$H$2:$H$101,D7,'Sales_Data'!$N$2:$N$101,"Completed") | G7: 46082 | H7: =COUNTIFS('Sales_Data'!$B$2:$B$101,">="&G7,'Sales_Data'!$B$2:$B$101,"<"&EDATE(G7,1),'Sales_Data'!$N$2:$N$101,"Completed") | I7: =SUMIFS('Sales_Data'!$L$2:$L$101,'Sales_Data'!$B$2:$B$101,">="&G7,'Sales_Data'!$B$2:$B$101,"<"&EDATE(G7,1),'Sales_Data'!$N$2:$N$101,"Completed")
A8: Average Order Value | B8: =AVERAGEIF('Sales_Data'!$N$2:$N$101,"Completed",'Sales_Data'!$L$2:$L$101) | G8: 46113 | H8: =COUNTIFS('Sales_Data'!$B$2:$B$101,">="&G8,'Sales_Data'!$B$2:$B$101,"<"&EDATE(G8,1),'Sales_Data'!$N$2:$N$101,"Completed") | I8: =SUMIFS('Sales_Data'!$L$2:$L$101,'Sales_Data'!$B$2:$B$101,">="&G8,'Sales_Data'!$B$2:$B$101,"<"&EDATE(G8,1),'Sales_Data'!$N$2:$N$101,"Completed")
A9: Completion Rate | B9: =COUNTIF('Sales_Data'!$N$2:$N$101,"Completed")/COUNTA('Sales_Data'!$N$2:$N$101) | G9: 46143 | H9: =COUNTIFS('Sales_Data'!$B$2:$B$101,">="&G9,'Sales_Data'!$B$2:$B$101,"<"&EDATE(G9,1),'Sales_Data'!$N$2:$N$101,"Completed") | I9: =SUMIFS('Sales_Data'!$L$2:$L$101,'Sales_Data'!$B$2:$B$101,">="&G9,'Sales_Data'!$B$2:$B$101,"<"&EDATE(G9,1),'Sales_Data'!$N$2:$N$101,"Completed")
G10: 46174 | H10: =COUNTIFS('Sales_Data'!$B$2:$B$101,">="&G10,'Sales_Data'!$B$2:$B$101,"<"&EDATE(G10,1),'Sales_Data'!$N$2:$N$101,"Completed") | I10: =SUMIFS('Sales_Data'!$L$2:$L$101,'Sales_Data'!$B$2:$B$101,">="&G10,'Sales_Data'!$B$2:$B$101,"<"&EDATE(G10,1),'Sales_Data'!$N$2:$N$101,"Completed")
G11: 46204 | H11: =COUNTIFS('Sales_Data'!$B$2:$B$101,">="&G11,'Sales_Data'!$B$2:$B$101,"<"&EDATE(G11,1),'Sales_Data'!$N$2:$N$101,"Completed") | I11: =SUMIFS('Sales_Data'!$L$2:$L$101,'Sales_Data'!$B$2:$B$101,">="&G11,'Sales_Data'!$B$2:$B$101,"<"&EDATE(G11,1),'Sales_Data'!$N$2:$N$101,"Completed")
A12: SALES BY CITY | D12: PAYMENT METHOD | G12: 46235 | H12: =COUNTIFS('Sales_Data'!$B$2:$B$101,">="&G12,'Sales_Data'!$B$2:$B$101,"<"&EDATE(G12,1),'Sales_Data'!$N$2:$N$101,"Completed") | I12: =SUMIFS('Sales_Data'!$L$2:$L$101,'Sales_Data'!$B$2:$B$101,">="&G12,'Sales_Data'!$B$2:$B$101,"<"&EDATE(G12,1),'Sales_Data'!$N$2:$N$101,"Completed")
A13: City | B13: Orders | C13: Sales | D13: Payment Method | E13: Orders | F13: Sales | G13: 46266 | H13: =COUNTIFS('Sales_Data'!$B$2:$B$101,">="&G13,'Sales_Data'!$B$2:$B$101,"<"&EDATE(G13,1),'Sales_Data'!$N$2:$N$101,"Completed") | I13: =SUMIFS('Sales_Data'!$L$2:$L$101,'Sales_Data'!$B$2:$B$101,">="&G13,'Sales_Data'!$B$2:$B$101,"<"&EDATE(G13,1),'Sales_Data'!$N$2:$N$101,"Completed")
A14: Berlin | B14: =COUNTIFS('Sales_Data'!$F$2:$F$101,A14,'Sales_Data'!$N$2:$N$101,"Completed") | C14: =SUMIFS('Sales_Data'!$L$2:$L$101,'Sales_Data'!$F$2:$F$101,A14,'Sales_Data'!$N$2:$N$101,"Completed") | D14: Bank Transfer | E14: =COUNTIFS('Sales_Data'!$M$2:$M$101,D14,'Sales_Data'!$N$2:$N$101,"Completed") | F14: =SUMIFS('Sales_Data'!$L$2:$L$101,'Sales_Data'!$M$2:$M$101,D14,'Sales_Data'!$N$2:$N$101,"Completed") | G14: 46296 | H14: =COUNTIFS('Sales_Data'!$B$2:$B$101,">="&G14,'Sales_Data'!$B$2:$B$101,"<"&EDATE(G14,1),'Sales_Data'!$N$2:$N$101,"Completed") | I14: =SUMIFS('Sales_Data'!$L$2:$L$101,'Sales_Data'!$B$2:$B$101,">="&G14,'Sales_Data'!$B$2:$B$101,"<"&EDATE(G14,1),'Sales_Data'!$N$2:$N$101,"Completed")
A15: Cologne | B15: =COUNTIFS('Sales_Data'!$F$2:$F$101,A15,'Sales_Data'!$N$2:$N$101,"Completed") | C15: =SUMIFS('Sales_Data'!$L$2:$L$101,'Sales_Data'!$F$2:$F$101,A15,'Sales_Data'!$N$2:$N$101,"Completed") | D15: Card | E15: =COUNTIFS('Sales_Data'!$M$2:$M$101,D15,'Sales_Data'!$N$2:$N$101,"Completed") | F15: =SUMIFS('Sales_Data'!$L$2:$L$101,'Sales_Data'!$M$2:$M$101,D15,'Sales_Data'!$N$2:$N$101,"Completed") | G15: 46327 | H15: =COUNTIFS('Sales_Data'!$B$2:$B$101,">="&G15,'Sales_Data'!$B$2:$B$101,"<"&EDATE(G15,1),'Sales_Data'!$N$2:$N$101,"Completed") | I15: =SUMIFS('Sales_Data'!$L$2:$L$101,'Sales_Data'!$B$2:$B$101,">="&G15,'Sales_Data'!$B$2:$B$101,"<"&EDATE(G15,1),'Sales_Data'!$N$2:$N$101,"Completed")
A16: Düsseldorf | B16: =COUNTIFS('Sales_Data'!$F$2:$F$101,A16,'Sales_Data'!$N$2:$N$101,"Completed") | C16: =SUMIFS('Sales_Data'!$L$2:$L$101,'Sales_Data'!$F$2:$F$101,A16,'Sales_Data'!$N$2:$N$101,"Completed") | D16: PayPal | E16: =COUNTIFS('Sales_Data'!$M$2:$M$101,D16,'Sales_Data'!$N$2:$N$101,"Completed") | F16: =SUMIFS('Sales_Data'!$L$2:$L$101,'Sales_Data'!$M$2:$M$101,D16,'Sales_Data'!$N$2:$N$101,"Completed") | G16: 46357 | H16: =COUNTIFS('Sales_Data'!$B$2:$B$101,">="&G16,'Sales_Data'!$B$2:$B$101,"<"&EDATE(G16,1),'Sales_Data'!$N$2:$N$101,"Completed") | I16: =SUMIFS('Sales_Data'!$L$2:$L$101,'Sales_Data'!$B$2:$B$101,">="&G16,'Sales_Data'!$B$2:$B$101,"<"&EDATE(G16,1),'Sales_Data'!$N$2:$N$101,"Completed")
A17: Frankfurt | B17: =COUNTIFS('Sales_Data'!$F$2:$F$101,A17,'Sales_Data'!$N$2:$N$101,"Completed") | C17: =SUMIFS('Sales_Data'!$L$2:$L$101,'Sales_Data'!$F$2:$F$101,A17,'Sales_Data'!$N$2:$N$101,"Completed")
A18: Hamburg | B18: =COUNTIFS('Sales_Data'!$F$2:$F$101,A18,'Sales_Data'!$N$2:$N$101,"Completed") | C18: =SUMIFS('Sales_Data'!$L$2:$L$101,'Sales_Data'!$F$2:$F$101,A18,'Sales_Data'!$N$2:$N$101,"Completed")
A19: Leipzig | B19: =COUNTIFS('Sales_Data'!$F$2:$F$101,A19,'Sales_Data'!$N$2:$N$101,"Completed") | C19: =SUMIFS('Sales_Data'!$L$2:$L$101,'Sales_Data'!$F$2:$F$101,A19,'Sales_Data'!$N$2:$N$101,"Completed")
A20: Munich | B20: =COUNTIFS('Sales_Data'!$F$2:$F$101,A20,'Sales_Data'!$N$2:$N$101,"Completed") | C20: =SUMIFS('Sales_Data'!$L$2:$L$101,'Sales_Data'!$F$2:$F$101,A20,'Sales_Data'!$N$2:$N$101,"Completed")
A21: Stuttgart | B21: =COUNTIFS('Sales_Data'!$F$2:$F$101,A21,'Sales_Data'!$N$2:$N$101,"Completed") | C21: =SUMIFS('Sales_Data'!$L$2:$L$101,'Sales_Data'!$F$2:$F$101,A21,'Sales_Data'!$N$2:$N$101,"Completed")
A24: TOP PRODUCTS | F24: ORDER STATUS
A25: Product | B25: Units | C25: Orders | D25: Sales | F25: Status | G25: Orders | H25: Sales
A26: Desk | B26: =SUMIFS('Sales_Data'!$I$2:$I$101,'Sales_Data'!$G$2:$G$101,A26,'Sales_Data'!$N$2:$N$101,"Completed") | C26: =COUNTIFS('Sales_Data'!$G$2:$G$101,A26,'Sales_Data'!$N$2:$N$101,"Completed") | D26: =SUMIFS('Sales_Data'!$L$2:$L$101,'Sales_Data'!$G$2:$G$101,A26,'Sales_Data'!$N$2:$N$101,"Completed") | F26: Completed | G26: =COUNTIF('Sales_Data'!$N$2:$N$101,F26) | H26: =SUMIF('Sales_Data'!$N$2:$N$101,F26,'Sales_Data'!$L$2:$L$101)
A27: Headphones | B27: =SUMIFS('Sales_Data'!$I$2:$I$101,'Sales_Data'!$G$2:$G$101,A27,'Sales_Data'!$N$2:$N$101,"Completed") | C27: =COUNTIFS('Sales_Data'!$G$2:$G$101,A27,'Sales_Data'!$N$2:$N$101,"Completed") | D27: =SUMIFS('Sales_Data'!$L$2:$L$101,'Sales_Data'!$G$2:$G$101,A27,'Sales_Data'!$N$2:$N$101,"Completed") | F27: Pending | G27: =COUNTIF('Sales_Data'!$N$2:$N$101,F27) | H27: =SUMIF('Sales_Data'!$N$2:$N$101,F27,'Sales_Data'!$L$2:$L$101)
A28: Keyboard | B28: =SUMIFS('Sales_Data'!$I$2:$I$101,'Sales_Data'!$G$2:$G$101,A28,'Sales_Data'!$N$2:$N$101,"Completed") | C28: =COUNTIFS('Sales_Data'!$G$2:$G$101,A28,'Sales_Data'!$N$2:$N$101,"Completed") | D28: =SUMIFS('Sales_Data'!$L$2:$L$101,'Sales_Data'!$G$2:$G$101,A28,'Sales_Data'!$N$2:$N$101,"Completed") | F28: Cancelled | G28: =COUNTIF('Sales_Data'!$N$2:$N$101,F28) | H28: =SUMIF('Sales_Data'!$N$2:$N$101,F28,'Sales_Data'!$L$2:$L$101)
A29: Laptop | B29: =SUMIFS('Sales_Data'!$I$2:$I$101,'Sales_Data'!$G$2:$G$101,A29,'Sales_Data'!$N$2:$N$101,"Completed") | C29: =COUNTIFS('Sales_Data'!$G$2:$G$101,A29,'Sales_Data'!$N$2:$N$101,"Completed") | D29: =SUMIFS('Sales_Data'!$L$2:$L$101,'Sales_Data'!$G$2:$G$101,A29,'Sales_Data'!$N$2:$N$101,"Completed")
A30: Monitor | B30: =SUMIFS('Sales_Data'!$I$2:$I$101,'Sales_Data'!$G$2:$G$101,A30,'Sales_Data'!$N$2:$N$101,"Completed") | C30: =COUNTIFS('Sales_Data'!$G$2:$G$101,A30,'Sales_Data'!$N$2:$N$101,"Completed") | D30: =SUMIFS('Sales_Data'!$L$2:$L$101,'Sales_Data'!$G$2:$G$101,A30,'Sales_Data'!$N$2:$N$101,"Completed")
A31: Mouse | B31: =SUMIFS('Sales_Data'!$I$2:$I$101,'Sales_Data'!$G$2:$G$101,A31,'Sales_Data'!$N$2:$N$101,"Completed") | C31: =COUNTIFS('Sales_Data'!$G$2:$G$101,A31,'Sales_Data'!$N$2:$N$101,"Completed") | D31: =SUMIFS('Sales_Data'!$L$2:$L$101,'Sales_Data'!$G$2:$G$101,A31,'Sales_Data'!$N$2:$N$101,"Completed")
A32: Office Chair | B32: =SUMIFS('Sales_Data'!$I$2:$I$101,'Sales_Data'!$G$2:$G$101,A32,'Sales_Data'!$N$2:$N$101,"Completed") | C32: =COUNTIFS('Sales_Data'!$G$2:$G$101,A32,'Sales_Data'!$N$2:$N$101,"Completed") | D32: =SUMIFS('Sales_Data'!$L$2:$L$101,'Sales_Data'!$G$2:$G$101,A32,'Sales_Data'!$N$2:$N$101,"Completed")
A33: Printer | B33: =SUMIFS('Sales_Data'!$I$2:$I$101,'Sales_Data'!$G$2:$G$101,A33,'Sales_Data'!$N$2:$N$101,"Completed") | C33: =COUNTIFS('Sales_Data'!$G$2:$G$101,A33,'Sales_Data'!$N$2:$N$101,"Completed") | D33: =SUMIFS('Sales_Data'!$L$2:$L$101,'Sales_Data'!$G$2:$G$101,A33,'Sales_Data'!$N$2:$N$101,"Completed")
A34: USB Hub | B34: =SUMIFS('Sales_Data'!$I$2:$I$101,'Sales_Data'!$G$2:$G$101,A34,'Sales_Data'!$N$2:$N$101,"Completed") | C34: =COUNTIFS('Sales_Data'!$G$2:$G$101,A34,'Sales_Data'!$N$2:$N$101,"Completed") | D34: =SUMIFS('Sales_Data'!$L$2:$L$101,'Sales_Data'!$G$2:$G$101,A34,'Sales_Data'!$N$2:$N$101,"Completed")
A35: Webcam | B35: =SUMIFS('Sales_Data'!$I$2:$I$101,'Sales_Data'!$G$2:$G$101,A35,'Sales_Data'!$N$2:$N$101,"Completed") | C35: =COUNTIFS('Sales_Data'!$G$2:$G$101,A35,'Sales_Data'!$N$2:$N$101,"Completed") | D35: =SUMIFS('Sales_Data'!$L$2:$L$101,'Sales_Data'!$G$2:$G$101,A35,'Sales_Data'!$N$2:$N$101,"Completed")

Sheet Guide

Sheet Guide1
A1: EXCEL SALES DASHBOARD — DETAILED GUIDE
A4: Topic | B4: Explanation
A5: 1. Dashboard purpose | B5: The dashboard converts the raw 100-order sales dataset into an executive view of revenue, completed sales, units, completion rate, trends and product/category/city performance.
A6: 2. KPI logic | B6: Total Orders = all orders. Total Sales = all order amounts. Completed Sales = sales from Completed orders only. Units Sold = quantity from Completed orders. Average Order Value = average Total_Amount for Completed orders. Completion Rate = Completed orders ÷ all orders.
A7: 3. Why use Completed orders? | B7: Pending and Cancelled orders are not finalized sales. Separating them prevents the performance view from overstating realized sales.
A8: 4. Monthly trend | B8: The monthly chart uses completed sales by month, making it easy to see strong and weak periods and identify seasonality.
A9: 5. Category analysis | B9: Compare Electronics, Accessories and Furniture by completed order count and sales value. This helps identify the most valuable product category.
A10: 6. City analysis | B10: Completed sales are summarized by city. Use this to identify stronger markets and possible locations for marketing or sales focus.
A11: 7. Payment analysis | B11: Shows completed order count and sales by Card, PayPal and Bank Transfer. This can help evaluate customer payment preferences.
A12: 8. Product analysis | B12: Top Products ranks products by completed sales and also provides units/orders in the Analysis sheet. This is useful for inventory and product strategy.
A13: 9. Status analysis | B13: Completed, Pending and Cancelled orders are separated so you can monitor conversion and potential revenue at risk.
A14: 10. Data sheet | B14: Sales_Data is formatted as an Excel Table called SalesData. Filters and calculated helper columns are included.
A15: 11. Data cleaning checks | B15: For a real dataset, check duplicate Order_IDs, blank dates, invalid quantities, negative prices/amounts, inconsistent category/status spelling and discount values outside the expected range.
... A17: 13. Interview explanation | B17: “I cleaned and structured the sales data, created KPI calculations, segmented performance by category, city, product, payment and status, analyzed monthly trends, and built a management dashboard to support data-driven decisions.”
